ctreeskit/__init__.py
ctreeskit/arraylake_tools/__init__.py
ctreeskit/arraylake_tools/common.py
ctreeskit/arraylake_tools/create.py
ctreeskit/arraylake_tools/initialize.py
ctreeskit/arraylake_tools/populate_dask.py
ctreeskit/arraylake_tools/datasets_config/categorical_raster_wtih_x_y.json
ctreeskit/arraylake_tools/datasets_config/categorical_raster_wtih_x_y_time.json
ctreeskit/arraylake_tools/datasets_config/conitnous_raster_with_x_y.json
ctreeskit/arraylake_tools/datasets_config/continous_raster_with_x_y_time.json
ctreeskit/xr_analyzer/__init__.py
ctreeskit/xr_analyzer/xr_common.py
ctreeskit/xr_analyzer/xr_spatial_processor_module.py
ctreeskit/xr_analyzer/xr_zonal_stats_module.py
ctreeskit-0.1.2.dist-info/METADATA
ctreeskit-0.1.2.dist-info/WHEEL
ctreeskit-0.1.2.dist-info/licenses/LICENSE
ctreeskit-0.1.2.dist-info/RECORD
