Metadata-Version: 2.4
Name: ctreeskit
Version: 0.1.2
Summary: CTrees toolkit for geospatial analysis and forest carbon monitoring. Core features include xarray-based analysis tools.
Project-URL: Homepage, https://github.com/ctrees-products/ctreeskit
Project-URL: Repository, https://github.com/ctrees-products/ctreeskit.git
Project-URL: Documentation, https://github.com/ctrees-products/ctreeskit#readme
Project-URL: Bug Tracker, https://github.com/ctrees-products/ctreeskit/issues
Author-email: Naomi Provost <nprovost@ctrees.org>
License-Expression: MIT
License-File: LICENSE
Keywords: biomass,carbon,geospatial,xarray,zonal-statistics
Classifier: Development Status :: 4 - Beta
Classifier: Intended Audience :: Science/Research
Classifier: License :: OSI Approved :: MIT License
Classifier: Programming Language :: Python :: 3
Classifier: Programming Language :: Python :: 3.12
Classifier: Topic :: Scientific/Engineering :: GIS
Requires-Python: >=3.11
Requires-Dist: arraylake>=0.15.0
Requires-Dist: cf-xarray>=0.10.0
Requires-Dist: geopandas>=0.14.1
Requires-Dist: icechunk>=0.2.2
Requires-Dist: numpy>=1.26.2
Requires-Dist: pandas>=2.1.4
Requires-Dist: pyproj>=3.6.1
Requires-Dist: python-dotenv>=1.0.0
Requires-Dist: rioxarray>=0.15.0
Requires-Dist: s3fs>=2025.3.0
Requires-Dist: scipy>=1.7.3
Requires-Dist: shapely>=2.0.2
Requires-Dist: xarray>=2025.03.1
Provides-Extra: all
Requires-Dist: dask>=2023.12.1; extra == 'all'
Requires-Dist: distributed>=2023.12.1; extra == 'all'
Requires-Dist: ipykernel>=6.27.1; extra == 'all'
Requires-Dist: ipyleaflet>=0.17.4; extra == 'all'
Provides-Extra: interactive
Requires-Dist: ipykernel>=6.27.1; extra == 'interactive'
Requires-Dist: ipyleaflet>=0.17.4; extra == 'interactive'
Provides-Extra: parallel
Requires-Dist: dask>=2023.12.1; extra == 'parallel'
Requires-Dist: distributed>=2023.12.1; extra == 'parallel'
